{
  "title": "Tromsø in August of 2021",
  "slug": "troms%C3%B8-in-august-of-2021-dd4e8aa59312",
  "postId": "dd4e8aa59312",
  "url": "https://weholt.medium.com/troms%C3%B8-in-august-of-2021-dd4e8aa59312",
  "guid": "https://medium.com/p/dd4e8aa59312",
  "pubDate": "Fri, 13 Aug 2021 14:17:56 GMT",
  "updated": "2021-08-13T14:17:56.508Z",
  "creator": "Thomas Weholt",
  "categories": [
    "norway",
    "landscape",
    "tromsø",
    "fujifilm",
    "travel"
  ],
  "imageCount": 65,
  "failedImageCount": 0,
  "failedImages": []
}
